prime_cli/__init__.py
prime_cli/client.py
prime_cli/config.py
prime_cli/main.py
prime_cli/py.typed
prime_cli/api/__init__.py
prime_cli/api/availability.py
prime_cli/api/client.py
prime_cli/api/disks.py
prime_cli/api/inference.py
prime_cli/api/pods.py
prime_cli/api/rl.py
prime_cli/commands/__init__.py
prime_cli/commands/availability.py
prime_cli/commands/config.py
prime_cli/commands/disks.py
prime_cli/commands/env.py
prime_cli/commands/evals.py
prime_cli/commands/images.py
prime_cli/commands/inference.py
prime_cli/commands/lab.py
prime_cli/commands/login.py
prime_cli/commands/pods.py
prime_cli/commands/registry.py
prime_cli/commands/rl.py
prime_cli/commands/sandbox.py
prime_cli/commands/teams.py
prime_cli/commands/tunnel.py
prime_cli/commands/upgrade.py
prime_cli/commands/whoami.py
prime_cli/core/__init__.py
prime_cli/core/client.py
prime_cli/core/config.py
prime_cli/helper/__init__.py
prime_cli/helper/short_id.py
prime_cli/utils/__init__.py
prime_cli/utils/config.py
prime_cli/utils/display.py
prime_cli/utils/env_metadata.py
prime_cli/utils/env_vars.py
prime_cli/utils/eval_push.py
prime_cli/utils/formatters.py
prime_cli/utils/prompt.py
prime_cli/utils/time_utils.py
prime_cli/utils/version_check.py
prime-0.5.27.dist-info/METADATA
prime-0.5.27.dist-info/WHEEL
prime-0.5.27.dist-info/entry_points.txt
prime-0.5.27.dist-info/licenses/LICENSE
prime-0.5.27.dist-info/RECORD
