Metadata-Version: 2.4
Name: prime
Version: 0.5.27
Summary: Prime Intellect CLI + SDK
Project-URL: Homepage, https://github.com/PrimeIntellect-ai/prime-cli
Project-URL: Documentation, https://github.com/PrimeIntellect-ai/prime-cli#readme
Project-URL: Repository, https://github.com/PrimeIntellect-ai/prime-cli.git
Project-URL: Changelog, https://github.com/PrimeIntellect-ai/prime-cli/blob/main/CHANGELOG.md
Author-email: Prime Intellect <contact@primeintellect.ai>
License-Expression: MIT
License-File: LICENSE
Keywords: cli,cloud,compute,gpu
Classifier: Development Status :: 4 - Beta
Classifier: Environment :: Console
Classifier: Intended Audience :: Developers
Classifier: License :: OSI Approved :: MIT License
Classifier: Operating System :: OS Independent
Classifier: Programming Language :: Python :: 3
Classifier: Programming Language :: Python :: 3.10
Classifier: Programming Language :: Python :: 3.11
Classifier: Programming Language :: Python :: 3.12
Classifier: Topic :: Software Development :: Libraries :: Python Modules
Requires-Python: <3.14,>=3.10
Requires-Dist: build>=1.0.0
Requires-Dist: cryptography>=41.0.0
Requires-Dist: httpx>=0.25.0
Requires-Dist: prime-evals>=0.1.3
Requires-Dist: prime-sandboxes>=0.1.0
Requires-Dist: prime-tunnel>=0.1.0
Requires-Dist: pydantic>=2.0.0
Requires-Dist: rich>=13.3.1
Requires-Dist: toml>=0.10.0
Requires-Dist: typer>=0.9.0
Requires-Dist: verifiers>=0.1.9.post1
Provides-Extra: dev
Requires-Dist: pytest>=7.0.0; extra == 'dev'
Requires-Dist: ruff>=0.13.1; extra == 'dev'
Requires-Dist: ty>=0.0.0a6; extra == 'dev'
Requires-Dist: types-toml>=0.10.0; extra == 'dev'
